Workbook

Sheet Settings
B2: TRADING JOURNAL SETTINGS
B4: Stock Commission (per share) | C4: 0
B5: Option Commission (per contract) | C5: 0.65

Sheet Dashboard
B2: TRADING PERFORMANCE DASHBOARD
B3: Real-time updates dynamically computed from your Trade Log sheet
B5: TOTAL NET PROFIT | E5: PSYCHOLOGICAL PERFORMANCE BREAKDOWN
B6: =SUM('Trade Log'!Q:Q) -> 1961.35
E7: Pre-Trade Emotion | F7: Trades Count | G7: Win Rate | H7: Total P&L
B8: WIN RATE | E8: Calm | F8: =COUNTIF('Trade Log'!R:R, "Calm") -> 3 | G8: =IF(F8>0, COUNTIFS('Trade Log'!R:R, "Calm", 'Trade Log'!Q:Q, ">0") / F8, 0) -> 1 | H8: =SUMIF('Trade Log'!R:R, "Calm", 'Trade Log'!Q:Q) -> 1980.9
B9: =IF(COUNTA('Trade Log'!D:D)-1>0, COUNTIF('Trade Log'!Q:Q,">0") / (COUNTIF('Trade Log'!Q:Q,">0") + COUNTIF('Trade Log'!Q:Q,"<0")), 0) -> 0.66666667 | E9: FOMO | F9: =COUNTIF('Trade Log'!R:R, "FOMO") -> 1 | G9: =IF(F9>0, COUNTIFS('Trade Log'!R:R, "FOMO", 'Trade Log'!Q:Q, ">0") / F9, 0) -> 1 | H9: =SUMIF('Trade Log'!R:R, "FOMO", 'Trade Log'!Q:Q) -> 846.75
E10: Greed | F10: =COUNTIF('Trade Log'!R:R, "Greed") -> 0 | G10: =IF(F10>0, COUNTIFS('Trade Log'!R:R, "Greed", 'Trade Log'!Q:Q, ">0") / F10, 0) -> 0 | H10: =SUMIF('Trade Log'!R:R, "Greed", 'Trade Log'!Q:Q) -> 0
B11: TOTAL TRADES | E11: Fear | F11: =COUNTIF('Trade Log'!R:R, "Fear") -> 1 | G11: =IF(F11>0, COUNTIFS('Trade Log'!R:R, "Fear", 'Trade Log'!Q:Q, ">0") / F11, 0) -> 0 | H11: =SUMIF('Trade Log'!R:R, "Fear", 'Trade Log'!Q:Q) -> -325
B12: =COUNTA('Trade Log'!D:D)-1 -> 6 | E12: Stressed | F12: =COUNTIF('Trade Log'!R:R, "Stressed") -> 1 | G12: =IF(F12>0, COUNTIFS('Trade Log'!R:R, "Stressed", 'Trade Log'!Q:Q, ">0") / F12, 0) -> 0 | H12: =SUMIF('Trade Log'!R:R, "Stressed", 'Trade Log'!Q:Q) -> -541.3
E13: Neutral | F13: =COUNTIF('Trade Log'!R:R, "Neutral") -> 0 | G13: =IF(F13>0, COUNTIFS('Trade Log'!R:R, "Neutral", 'Trade Log'!Q:Q, ">0") / F13, 0) -> 0 | H13: =SUMIF('Trade Log'!R:R, "Neutral", 'Trade Log'!Q:Q) -> 0
B14: PROFIT FACTOR
B15: =IF(SUMIF('Trade Log'!Q:Q,"<0")<>0, ABS(SUMIF('Trade Log'!Q:Q,">0") / SUMIF('Trade Log'!Q:Q,"<0")), SUMIF('Trade Log'!Q:Q,">0")) -> 3.264054
B17: AVG RISK-REWARD RATIO
B18: =AVERAGE('Trade Log'!O:O) -> 2.135

Sheet Trade Log
A1: Entry Date | B1: Exit Date | C1: Asset Class | D1: Ticker | E1: Direction | F1: Option Strategy | G1: Strike Price(s) | H1: Expiry Date | I1: Days in Trade | J1: Days to Expiry | K1: Quantity | L1: Entry Price | M1: Stop Loss | N1: Exit Price | O1: Risk-Reward Ratio | P1: Fees & Comm. | Q1: Net P&L | R1: Emotion Pre | S1: Emotion Post | T1: Setup Reason | U1: Notes
A2: 46152.604 | B2: 46157.833 | C2: Stock | D2: AAPL | E2: Buy/Long | F2: N/A | I2: =IF(OR(A2="", B2=""), "", INT(B2-A2)) -> 5 | J2: =IF(OR(A2="", H2=""), "", INT(H2-A2)) | K2: 100 | L2: 172.5 | M2: 170 | N2: 178.2 | O2: =IF(OR(L2="", N2="", M2="", M2=L2), "", ROUND(ABS(N2-L2)/ABS(L2-M2), 2)) -> 2.28 | P2: =IF(C2="Stock", Settings!$C$4 * K2, IF(C2="Option", Settings!$C$5 * K2, 0)) -> 0 | Q2: =IF(E2="Buy/Long", (N2-L2)*K2-P2, (L2-N2)*K2-P2) -> 570 | R2: Calm | S2: Calm | T2: Breakout | U2: Perfect textbook breakout of the 50 DMA.
A3: 46154.76 | B3: 46161.583 | C3: Option | D3: TSLA | E3: Buy/Long | F3: Single Option | G3: 220 Call | H3: 46171.167 | I3: =IF(OR(A3="", B3=""), "", INT(B3-A3)) -> 6 | J3: =IF(OR(A3="", H3=""), "", INT(H3-A3)) -> 16 | K3: 5 | L3: 4.5 | M3: 3.5 | N3: 6.2 | O3: =IF(OR(L3="", N3="", M3="", M3=L3), "", ROUND(ABS(N3-L3)/ABS(L3-M3), 2)) -> 1.7 | P3: =IF(C3="Stock", Settings!$C$4 * K3, IF(C3="Option", Settings!$C$5 * K3, 0)) -> 3.25 | Q3: =IF(E3="Buy/Long", (N3-L3)*K3*100-P3, (L3-N3)*K3*100-P3) -> 846.75 | R3: FOMO | S3: Greed | T3: Trend Following | U3: Surged up. Chased slightly due to FOMO.
A4: 46156.576 | B4: 46170.812 | C4: Option | D4: SPY | E4: Sell/Short | F4: Credit Spread | G4: 510/505 Put Spread | H4: 46171.167 | I4: =IF(OR(A4="", B4=""), "", INT(B4-A4)) -> 14 | J4: =IF(OR(A4="", H4=""), "", INT(H4-A4)) -> 14 | K4: 10 | L4: 1.2 | M4: 1.8 | N4: 0.3 | O4: =IF(OR(L4="", N4="", M4="", M4=L4), "", ROUND(ABS(N4-L4)/ABS(L4-M4), 2)) -> 1.5 | P4: =IF(C4="Stock", Settings!$C$4 * K4, IF(C4="Option", Settings!$C$5 * K4, 0)) -> 6.5 | Q4: =IF(E4="Buy/Long", (N4-L4)*K4*100-P4, (L4-N4)*K4*100-P4) -> 893.5 | R4: Calm | S4: Calm | T4: Support/Resistance | U4: Sold put credit spread at solid horizontal support. Worked perfectly.
A5: 46160.646 | B5: 46164.667 | C5: Option | D5: MSFT | E5: Buy/Long | F5: Debit Spread | G5: 420/425 Call Spread | H5: 46171.167 | I5: =IF(OR(A5="", B5=""), "", INT(B5-A5)) -> 4 | J5: =IF(OR(A5="", H5=""), "", INT(H5-A5)) -> 10 | K5: 4 | L5: 2.1 | M5: 1.5 | N5: 3.4 | O5: =IF(OR(L5="", N5="", M5="", M5=L5), "", ROUND(ABS(N5-L5)/ABS(L5-M5), 2)) -> 2.17 | P5: =IF(C5="Stock", Settings!$C$4 * K5, IF(C5="Option", Settings!$C$5 * K5, 0)) -> 2.6 | Q5: =IF(E5="Buy/Long", (N5-L5)*K5*100-P5, (L5-N5)*K5*100-P5) -> 517.4 | R5: Calm | S5: Stressed | T5: Trend Following | U5: Long term call debit spread capturing upward continuation.
A6: 46162.722 | B6: 46165.792 | C6: Option | D6: NVDA | E6: Buy/Long | F6: Calendar Spread | G6: 920 Call | H6: 46171.167 | I6: =IF(OR(A6="", B6=""), "", INT(B6-A6)) -> 3 | J6: =IF(OR(A6="", H6=""), "", INT(H6-A6)) -> 8 | K6: 2 | L6: 4.8 | M6: 5.5 | N6: 2.1 | O6: =IF(OR(L6="", N6="", M6="", M6=L6), "", ROUND(ABS(N6-L6)/ABS(L6-M6), 2)) -> 3.86 | P6: =IF(C6="Stock", Settings!$C$4 * K6, IF(C6="Option", Settings!$C$5 * K6, 0)) -> 1.3 | Q6: =IF(E6="Buy/Long", (N6-L6)*K6*100-P6, (L6-N6)*K6*100-P6) -> -541.3 | R6: Stressed | S6: Calm | T6: News/Catalyst | U6: Traded pre-earnings calendar spread. Implied volatility crush arbitrage caused a solid loss.
A7: 46164.819 | B7: 46165.562 | C7: Stock | D7: AMD | E7: Buy/Long | F7: N/A | I7: =IF(OR(A7="", B7=""), "", INT(B7-A7)) -> 0 | J7: =IF(OR(A7="", H7=""), "", INT(H7-A7)) | K7: 50 | L7: 165 | M7: 170 | N7: 158.5 | O7: =IF(OR(L7="", N7="", M7="", M7=L7), "", ROUND(ABS(N7-L7)/ABS(L7-M7), 2)) -> 1.3 | P7: =IF(C7="Stock", Settings!$C$4 * K7, IF(C7="Option", Settings!$C$5 * K7, 0)) -> 0 | Q7: =IF(E7="Buy/Long", (N7-L7)*K7-P7, (L7-N7)*K7-P7) -> -325 | R7: Fear | S7: Stressed | T7: FOMO (No Setup) | U7: Traded without clear setup feeling extremely anxious. Stop hit quickly causing solid loss.
I8: =IF(OR(A8="", B8=""), "", INT(B8-A8)) | J8: =IF(OR(A8="", H8=""), "", INT(H8-A8)) | O8: =IF(OR(L8="", N8="", M8="", M8=L8), "", ROUND(ABS(N8-L8)/ABS(L8-M8), 2)) | P8: =IF(C8="Stock", Settings!$C$4 * K8, IF(C8="Option", Settings!$C$5 * K8, 0)) -> 0 | Q8: =IF(C8="Stock", IF(E8="Buy/Long", (N8-L8)*K8-P8, (L8-N8)*K8-P8), IF(C8="Option", IF(E8="Buy/Long", (N8-L8)*K8*100-P8, (L8-N8)*K8*100-P8), ""))
I9: =IF(OR(A9="", B9=""), "", INT(B9-A9)) | J9: =IF(OR(A9="", H9=""), "", INT(H9-A9)) | O9: =IF(OR(L9="", N9="", M9="", M9=L9), "", ROUND(ABS(N9-L9)/ABS(L9-M9), 2)) | P9: =IF(C9="Stock", Settings!$C$4 * K9, IF(C9="Option", Settings!$C$5 * K9, 0)) -> 0 | Q9: =IF(C9="Stock", IF(E9="Buy/Long", (N9-L9)*K9-P9, (L9-N9)*K9-P9), IF(C9="Option", IF(E9="Buy/Long", (N9-L9)*K9*100-P9, (L9-N9)*K9*100-P9), ""))
I10: =IF(OR(A10="", B10=""), "", INT(B10-A10)) | J10: =IF(OR(A10="", H10=""), "", INT(H10-A10)) | O10: =IF(OR(L10="", N10="", M10="", M10=L10), "", ROUND(ABS(N10-L10)/ABS(L10-M10), 2)) | P10: =IF(C10="Stock", Settings!$C$4 * K10, IF(C10="Option", Settings!$C$5 * K10, 0)) -> 0 | Q10: =IF(C10="Stock", IF(E10="Buy/Long", (N10-L10)*K10-P10, (L10-N10)*K10-P10), IF(C10="Option", IF(E10="Buy/Long", (N10-L10)*K10*100-P10, (L10-N10)*K10*100-P10), ""))
I11: =IF(OR(A11="", B11=""), "", INT(B11-A11)) | J11: =IF(OR(A11="", H11=""), "", INT(H11-A11)) | O11: =IF(OR(L11="", N11="", M11="", M11=L11), "", ROUND(ABS(N11-L11)/ABS(L11-M11), 2)) | P11: =IF(C11="Stock", Settings!$C$4 * K11, IF(C11="Option", Settings!$C$5 * K11, 0)) -> 0 | Q11: =IF(C11="Stock", IF(E11="Buy/Long", (N11-L11)*K11-P11, (L11-N11)*K11-P11), IF(C11="Option", IF(E11="Buy/Long", (N11-L11)*K11*100-P11, (L11-N11)*K11*100-P11), ""))
I12: =IF(OR(A12="", B12=""), "", INT(B12-A12)) | J12: =IF(OR(A12="", H12=""), "", INT(H12-A12)) | O12: =IF(OR(L12="", N12="", M12="", M12=L12), "", ROUND(ABS(N12-L12)/ABS(L12-M12), 2)) | P12: =IF(C12="Stock", Settings!$C$4 * K12, IF(C12="Option", Settings!$C$5 * K12, 0)) -> 0 | Q12: =IF(C12="Stock", IF(E12="Buy/Long", (N12-L12)*K12-P12, (L12-N12)*K12-P12), IF(C12="Option", IF(E12="Buy/Long", (N12-L12)*K12*100-P12, (L12-N12)*K12*100-P12), ""))
I13: =IF(OR(A13="", B13=""), "", INT(B13-A13)) | J13: =IF(OR(A13="", H13=""), "", INT(H13-A13)) | O13: =IF(OR(L13="", N13="", M13="", M13=L13), "", ROUND(ABS(N13-L13)/ABS(L13-M13), 2)) | P13: =IF(C13="Stock", Settings!$C$4 * K13, IF(C13="Option", Settings!$C$5 * K13, 0)) -> 0 | Q13: =IF(C13="Stock", IF(E13="Buy/Long", (N13-L13)*K13-P13, (L13-N13)*K13-P13), IF(C13="Option", IF(E13="Buy/Long", (N13-L13)*K13*100-P13, (L13-N13)*K13*100-P13), ""))
I14: =IF(OR(A14="", B14=""), "", INT(B14-A14)) | J14: =IF(OR(A14="", H14=""), "", INT(H14-A14)) | O14: =IF(OR(L14="", N14="", M14="", M14=L14), "", ROUND(ABS(N14-L14)/ABS(L14-M14), 2)) | P14: =IF(C14="Stock", Settings!$C$4 * K14, IF(C14="Option", Settings!$C$5 * K14, 0)) -> 0 | Q14: =IF(C14="Stock", IF(E14="Buy/Long", (N14-L14)*K14-P14, (L14-N14)*K14-P14), IF(C14="Option", IF(E14="Buy/Long", (N14-L14)*K14*100-P14, (L14-N14)*K14*100-P14), ""))
I15: =IF(OR(A15="", B15=""), "", INT(B15-A15)) | J15: =IF(OR(A15="", H15=""), "", INT(H15-A15)) | O15: =IF(OR(L15="", N15="", M15="", M15=L15), "", ROUND(ABS(N15-L15)/ABS(L15-M15), 2)) | P15: =IF(C15="Stock", Settings!$C$4 * K15, IF(C15="Option", Settings!$C$5 * K15, 0)) -> 0 | Q15: =IF(C15="Stock", IF(E15="Buy/Long", (N15-L15)*K15-P15, (L15-N15)*K15-P15), IF(C15="Option", IF(E15="Buy/Long", (N15-L15)*K15*100-P15, (L15-N15)*K15*100-P15), ""))
I16: =IF(OR(A16="", B16=""), "", INT(B16-A16)) | J16: =IF(OR(A16="", H16=""), "", INT(H16-A16)) | O16: =IF(OR(L16="", N16="", M16="", M16=L16), "", ROUND(ABS(N16-L16)/ABS(L16-M16), 2)) | P16: =IF(C16="Stock", Settings!$C$4 * K16, IF(C16="Option", Settings!$C$5 * K16, 0)) -> 0 | Q16: =IF(C16="Stock", IF(E16="Buy/Long", (N16-L16)*K16-P16, (L16-N16)*K16-P16), IF(C16="Option", IF(E16="Buy/Long", (N16-L16)*K16*100-P16, (L16-N16)*K16*100-P16), ""))
I17: =IF(OR(A17="", B17=""), "", INT(B17-A17)) | J17: =IF(OR(A17="", H17=""), "", INT(H17-A17)) | O17: =IF(OR(L17="", N17="", M17="", M17=L17), "", ROUND(ABS(N17-L17)/ABS(L17-M17), 2)) | P17: =IF(C17="Stock", Settings!$C$4 * K17, IF(C17="Option", Settings!$C$5 * K17, 0)) -> 0 | Q17: =IF(C17="Stock", IF(E17="Buy/Long", (N17-L17)*K17-P17, (L17-N17)*K17-P17), IF(C17="Option", IF(E17="Buy/Long", (N17-L17)*K17*100-P17, (L17-N17)*K17*100-P17), ""))
I18: =IF(OR(A18="", B18=""), "", INT(B18-A18)) | J18: =IF(OR(A18="", H18=""), "", INT(H18-A18)) | O18: =IF(OR(L18="", N18="", M18="", M18=L18), "", ROUND(ABS(N18-L18)/ABS(L18-M18), 2)) | P18: =IF(C18="Stock", Settings!$C$4 * K18, IF(C18="Option", Settings!$C$5 * K18, 0)) -> 0 | Q18: =IF(C18="Stock", IF(E18="Buy/Long", (N18-L18)*K18-P18, (L18-N18)*K18-P18), IF(C18="Option", IF(E18="Buy/Long", (N18-L18)*K18*100-P18, (L18-N18)*K18*100-P18), ""))
I19: =IF(OR(A19="", B19=""), "", INT(B19-A19)) | J19: =IF(OR(A19="", H19=""), "", INT(H19-A19)) | O19: =IF(OR(L19="", N19="", M19="", M19=L19), "", ROUND(ABS(N19-L19)/ABS(L19-M19), 2)) | P19: =IF(C19="Stock", Settings!$C$4 * K19, IF(C19="Option", Settings!$C$5 * K19, 0)) -> 0 | Q19: =IF(C19="Stock", IF(E19="Buy/Long", (N19-L19)*K19-P19, (L19-N19)*K19-P19), IF(C19="Option", IF(E19="Buy/Long", (N19-L19)*K19*100-P19, (L19-N19)*K19*100-P19), ""))
... I100: =IF(OR(A100="", B100=""), "", INT(B100-A100)) | J100: =IF(OR(A100="", H100=""), "", INT(H100-A100)) | O100: =IF(OR(L100="", N100="", M100="", M100=L100), "", ROUND(ABS(N100-L100)/ABS(L100-M100), 2)) | P100: =IF(C100="Stock", Settings!$C$4 * K100, IF(C100="Option", Settings!$C$5 * K100, 0)) -> 0 | Q100: =IF(C100="Stock", IF(E100="Buy/Long", (N100-L100)*K100-P100, (L100-N100)*K100-P100), IF(C100="Option", IF(E100="Buy/Long", (N100-L100)*K100*100-P100, (L100-N100)*K100*100-P100), ""))

Sheet Calendar View
B2: ="DAILY TRADING P&L CALENDAR - " & TEXT(TODAY(), "MMMM YYYY") -> DAILY TRADING P&L CALENDAR - May 2026
B4: Sunday | C4: Monday | D4: Tuesday | E4: Wednesday | F4: Thursday | G4: Friday | H4: Saturday | I4: MONTH TOTAL P&L
B5: =DATE(YEAR(TODAY()), MONTH(TODAY()), 1) - WEEKDAY(DATE(YEAR(TODAY()), MONTH(TODAY()), 1)) + 1 -> 46138 | C5: =B5+1 -> 46139 | D5: =C5+1 -> 46140 | E5: =D5+1 -> 46141 | F5: =E5+1 -> 46142 | G5: =F5+1 -> 46143 | H5: =G5+1 -> 46144 | I5: =SUM(B6:H6, B8:H8, B10:H10, B12:H12, B14:H14) -> 1961.35
B6: =SUMIFS('Trade Log'!Q:Q, 'Trade Log'!A:A, ">="&B5, 'Trade Log'!A:A, "<"&(B5+1)) -> 0 | C6: =SUMIFS('Trade Log'!Q:Q, 'Trade Log'!A:A, ">="&C5, 'Trade Log'!A:A, "<"&(C5+1)) -> 0 | D6: =SUMIFS('Trade Log'!Q:Q, 'Trade Log'!A:A, ">="&D5, 'Trade Log'!A:A, "<"&(D5+1)) -> 0 | E6: =SUMIFS('Trade Log'!Q:Q, 'Trade Log'!A:A, ">="&E5, 'Trade Log'!A:A, "<"&(E5+1)) -> 0 | F6: =SUMIFS('Trade Log'!Q:Q, 'Trade Log'!A:A, ">="&F5, 'Trade Log'!A:A, "<"&(F5+1)) -> 0 | G6: =SUMIFS('Trade Log'!Q:Q, 'Trade Log'!A:A, ">="&G5, 'Trade Log'!A:A, "<"&(G5+1)) -> 0 | H6: =SUMIFS('Trade Log'!Q:Q, 'Trade Log'!A:A, ">="&H5, 'Trade Log'!A:A, "<"&(H5+1)) -> 0
B7: =H5+1 -> 46145 | C7: =B7+1 -> 46146 | D7: =C7+1 -> 46147 | E7: =D7+1 -> 46148 | F7: =E7+1 -> 46149 | G7: =F7+1 -> 46150 | H7: =G7+1 -> 46151
B8: =SUMIFS('Trade Log'!Q:Q, 'Trade Log'!A:A, ">="&B7, 'Trade Log'!A:A, "<"&(B7+1)) -> 0 | C8: =SUMIFS('Trade Log'!Q:Q, 'Trade Log'!A:A, ">="&C7, 'Trade Log'!A:A, "<"&(C7+1)) -> 0 | D8: =SUMIFS('Trade Log'!Q:Q, 'Trade Log'!A:A, ">="&D7, 'Trade Log'!A:A, "<"&(D7+1)) -> 0 | E8: =SUMIFS('Trade Log'!Q:Q, 'Trade Log'!A:A, ">="&E7, 'Trade Log'!A:A, "<"&(E7+1)) -> 0 | F8: =SUMIFS('Trade Log'!Q:Q, 'Trade Log'!A:A, ">="&F7, 'Trade Log'!A:A, "<"&(F7+1)) -> 0 | G8: =SUMIFS('Trade Log'!Q:Q, 'Trade Log'!A:A, ">="&G7, 'Trade Log'!A:A, "<"&(G7+1)) -> 0 | H8: =SUMIFS('Trade Log'!Q:Q, 'Trade Log'!A:A, ">="&H7, 'Trade Log'!A:A, "<"&(H7+1)) -> 0
B9: =H7+1 -> 46152 | C9: =B9+1 -> 46153 | D9: =C9+1 -> 46154 | E9: =D9+1 -> 46155 | F9: =E9+1 -> 46156 | G9: =F9+1 -> 46157 | H9: =G9+1 -> 46158
B10: =SUMIFS('Trade Log'!Q:Q, 'Trade Log'!A:A, ">="&B9, 'Trade Log'!A:A, "<"&(B9+1)) -> 570 | C10: =SUMIFS('Trade Log'!Q:Q, 'Trade Log'!A:A, ">="&C9, 'Trade Log'!A:A, "<"&(C9+1)) -> 0 | D10: =SUMIFS('Trade Log'!Q:Q, 'Trade Log'!A:A, ">="&D9, 'Trade Log'!A:A, "<"&(D9+1)) -> 846.75 | E10: =SUMIFS('Trade Log'!Q:Q, 'Trade Log'!A:A, ">="&E9, 'Trade Log'!A:A, "<"&(E9+1)) -> 0 | F10: =SUMIFS('Trade Log'!Q:Q, 'Trade Log'!A:A, ">="&F9, 'Trade Log'!A:A, "<"&(F9+1)) -> 893.5 | G10: =SUMIFS('Trade Log'!Q:Q, 'Trade Log'!A:A, ">="&G9, 'Trade Log'!A:A, "<"&(G9+1)) -> 0 | H10: =SUMIFS('Trade Log'!Q:Q, 'Trade Log'!A:A, ">="&H9, 'Trade Log'!A:A, "<"&(H9+1)) -> 0
B11: =H9+1 -> 46159 | C11: =B11+1 -> 46160 | D11: =C11+1 -> 46161 | E11: =D11+1 -> 46162 | F11: =E11+1 -> 46163 | G11: =F11+1 -> 46164 | H11: =G11+1 -> 46165
B12: =SUMIFS('Trade Log'!Q:Q, 'Trade Log'!A:A, ">="&B11, 'Trade Log'!A:A, "<"&(B11+1)) -> 0 | C12: =SUMIFS('Trade Log'!Q:Q, 'Trade Log'!A:A, ">="&C11, 'Trade Log'!A:A, "<"&(C11+1)) -> 517.4 | D12: =SUMIFS('Trade Log'!Q:Q, 'Trade Log'!A:A, ">="&D11, 'Trade Log'!A:A, "<"&(D11+1)) -> 0 | E12: =SUMIFS('Trade Log'!Q:Q, 'Trade Log'!A:A, ">="&E11, 'Trade Log'!A:A, "<"&(E11+1)) -> -541.3 | F12: =SUMIFS('Trade Log'!Q:Q, 'Trade Log'!A:A, ">="&F11, 'Trade Log'!A:A, "<"&(F11+1)) -> 0 | G12: =SUMIFS('Trade Log'!Q:Q, 'Trade Log'!A:A, ">="&G11, 'Trade Log'!A:A, "<"&(G11+1)) -> -325 | H12: =SUMIFS('Trade Log'!Q:Q, 'Trade Log'!A:A, ">="&H11, 'Trade Log'!A:A, "<"&(H11+1)) -> 0
B13: =H11+1 -> 46166 | C13: =B13+1 -> 46167 | D13: =C13+1 -> 46168 | E13: =D13+1 -> 46169 | F13: =E13+1 -> 46170 | G13: =F13+1 -> 46171 | H13: =G13+1 -> 46172
B14: =SUMIFS('Trade Log'!Q:Q, 'Trade Log'!A:A, ">="&B13, 'Trade Log'!A:A, "<"&(B13+1)) -> 0 | C14: =SUMIFS('Trade Log'!Q:Q, 'Trade Log'!A:A, ">="&C13, 'Trade Log'!A:A, "<"&(C13+1)) -> 0 | D14: =SUMIFS('Trade Log'!Q:Q, 'Trade Log'!A:A, ">="&D13, 'Trade Log'!A:A, "<"&(D13+1)) -> 0 | E14: =SUMIFS('Trade Log'!Q:Q, 'Trade Log'!A:A, ">="&E13, 'Trade Log'!A:A, "<"&(E13+1)) -> 0 | F14: =SUMIFS('Trade Log'!Q:Q, 'Trade Log'!A:A, ">="&F13, 'Trade Log'!A:A, "<"&(F13+1)) -> 0 | G14: =SUMIFS('Trade Log'!Q:Q, 'Trade Log'!A:A, ">="&G13, 'Trade Log'!A:A, "<"&(G13+1)) -> 0 | H14: =SUMIFS('Trade Log'!Q:Q, 'Trade Log'!A:A, ">="&H13, 'Trade Log'!A:A, "<"&(H13+1)) -> 0

Sheet Yearly Review
B2: ="YEARLY PERFORMANCE REVIEW - " & YEAR(TODAY()) -> YEARLY PERFORMANCE REVIEW - 2026
B5: JANUARY | D5: FEBRUARY | F5: MARCH | H5: APRIL | J5: YEAR TOTAL P&L
B6: =SUMIFS('Trade Log'!Q:Q, 'Trade Log'!A:A, ">="&DATE(YEAR(TODAY()),1,1), 'Trade Log'!A:A, "<"&DATE(YEAR(TODAY()),2,1)) -> 0 | D6: =SUMIFS('Trade Log'!Q:Q, 'Trade Log'!A:A, ">="&DATE(YEAR(TODAY()),2,1), 'Trade Log'!A:A, "<"&DATE(YEAR(TODAY()),3,1)) -> 0 | F6: =SUMIFS('Trade Log'!Q:Q, 'Trade Log'!A:A, ">="&DATE(YEAR(TODAY()),3,1), 'Trade Log'!A:A, "<"&DATE(YEAR(TODAY()),4,1)) -> 0 | H6: =SUMIFS('Trade Log'!Q:Q, 'Trade Log'!A:A, ">="&DATE(YEAR(TODAY()),4,1), 'Trade Log'!A:A, "<"&DATE(YEAR(TODAY()),5,1)) -> 0 | J6: =SUM(B6, D6, F6, H6, B9, D9, F9, H9, B12, D12, F12, H12) -> 1961.35
B8: MAY | D8: JUNE | F8: JULY | H8: AUGUST
B9: =SUMIFS('Trade Log'!Q:Q, 'Trade Log'!A:A, ">="&DATE(YEAR(TODAY()),5,1), 'Trade Log'!A:A, "<"&DATE(YEAR(TODAY()),6,1)) -> 1961.35 | D9: =SUMIFS('Trade Log'!Q:Q, 'Trade Log'!A:A, ">="&DATE(YEAR(TODAY()),6,1), 'Trade Log'!A:A, "<"&DATE(YEAR(TODAY()),7,1)) -> 0 | F9: =SUMIFS('Trade Log'!Q:Q, 'Trade Log'!A:A, ">="&DATE(YEAR(TODAY()),7,1), 'Trade Log'!A:A, "<"&DATE(YEAR(TODAY()),8,1)) -> 0 | H9: =SUMIFS('Trade Log'!Q:Q, 'Trade Log'!A:A, ">="&DATE(YEAR(TODAY()),8,1), 'Trade Log'!A:A, "<"&DATE(YEAR(TODAY()),9,1)) -> 0
B11: SEPTEMBER | D11: OCTOBER | F11: NOVEMBER | H11: DECEMBER
B12: =SUMIFS('Trade Log'!Q:Q, 'Trade Log'!A:A, ">="&DATE(YEAR(TODAY()),9,1), 'Trade Log'!A:A, "<"&DATE(YEAR(TODAY()),10,1)) -> 0 | D12: =SUMIFS('Trade Log'!Q:Q, 'Trade Log'!A:A, ">="&DATE(YEAR(TODAY()),10,1), 'Trade Log'!A:A, "<"&DATE(YEAR(TODAY()),11,1)) -> 0 | F12: =SUMIFS('Trade Log'!Q:Q, 'Trade Log'!A:A, ">="&DATE(YEAR(TODAY()),11,1), 'Trade Log'!A:A, "<"&DATE(YEAR(TODAY()),12,1)) -> 0 | H12: =SUMIFS('Trade Log'!Q:Q, 'Trade Log'!A:A, ">="&DATE(YEAR(TODAY()),12,1), 'Trade Log'!A:A, "<"&DATE(YEAR(TODAY())+1,1,1)) -> 0
